djangocms_concurrent_users/__init__.py
djangocms_concurrent_users/apps.py
djangocms_concurrent_users/cms_toolbars.py
djangocms_concurrent_users/models.py
djangocms_concurrent_users/urls.py
djangocms_concurrent_users/views.py
djangocms_concurrent_users/locale/de/LC_MESSAGES/django.mo
djangocms_concurrent_users/locale/de/LC_MESSAGES/django.po
djangocms_concurrent_users/migrations/0001_initial.py
djangocms_concurrent_users/migrations/__init__.py
djangocms_concurrent_users/static/css/concurrent_users.css
djangocms_concurrent_users/static/fonts/FontAwesome.otf
djangocms_concurrent_users/static/fonts/fontawesome-webfont.eot
djangocms_concurrent_users/static/fonts/fontawesome-webfont.svg
djangocms_concurrent_users/static/fonts/fontawesome-webfont.ttf
djangocms_concurrent_users/static/fonts/fontawesome-webfont.woff
djangocms_concurrent_users/static/fonts/fontawesome-webfont.woff2
djangocms_concurrent_users/static/js/concurrent_users.js
djangocms_concurrent_users/templates/djangocms_concurrent_users/concurrency_button.html
djangocms_concurrent_users-0.0.5.dist-info/DESCRIPTION.rst
djangocms_concurrent_users-0.0.5.dist-info/METADATA
djangocms_concurrent_users-0.0.5.dist-info/RECORD
djangocms_concurrent_users-0.0.5.dist-info/WHEEL
djangocms_concurrent_users-0.0.5.dist-info/metadata.json
djangocms_concurrent_users-0.0.5.dist-info/top_level.txt
