Metadata-Version: 2.0
Name: djangocms-concurrent-users
Version: 0.0.5
Summary: Django-CMS Plugin for blocking pages which are edited by another user
Home-page: https://github.com/Blueshoe/djangocms-concurrent-users
Author: Michael Schilonka
Author-email: michael@blueshoe.de
License: MIT
Platform: UNKNOWN
Classifier: Framework :: Django
Classifier: Intended Audience :: Developers
Classifier: Operating System :: OS Independent
Classifier: Programming Language :: Python
Classifier: Topic :: Internet :: WWW/HTTP
Requires-Dist: Django (>=1.8)
Requires-Dist: django-cms (>=3.4)
Requires-Dist: django-filer (>=1.2.0)
